{"type":"idp","description":"Description","country":"Country","ADM1":"ADM1","ADM2":"ADM2","ADM3":"ADM3","ADM4":"ADM4","name":"Name","pcode":"pcode","location":"Latitude,Longitude"}
{"type":"idp","description":"IDP Camp","country":"Syria","ADM1":"As Suwayda'","ADM2":"As-Sweida","ADM3":"As-Sweida","ADM4":"Kherba","name":"Kharaba Church East IDP Camp ","pcode":"SY130000C6150","location":"32.588,36.447"}
{"type":"idp","description":"IDP Camp","country":"Syria","ADM1":"As Suwayda","ADM2":"As-Sweida","ADM3":"As-Sweida","ADM4":"Kherba","name":"Kharaba IDP Camp","pcode":"SY130000C6150","location":"32.583,36.439"}
{"type":"idp","description":"IDP Camp","country":"Syria","ADM1":"Damascus Countryside","ADM2":"Duma","ADM3":"Sabe Byar","ADM4":"Sabe Byar","name":"Khashm al Ghardush IDP Camp","pcode":"SY030202C2345","location":"32.857,37.82"}
{"type":"idp","description":"IDP Camp","country":"Syria","ADM1":"Damascus Countryside","ADM2":"Duma","ADM3":"Sabe Byar","ADM4":"Sabe Byar","name":"Ruqban Border Crossing IDP Camp","pcode":"SY030202C2345","location":"33.311,38.674"}
{"type":"idp","description":"IDP Camp","country":"Syria","ADM1":"Dar'a","ADM2":"Dar'a","ADM3":"Ash-Shajara","ADM4":"Ash-Shajara","name":"Ash Shajarah IDP Camp 01","pcode":"SY120003C6021","location":"32.775,35.886"}
{"type":"idp","description":"IDP Camp","country":"Syria","ADM1":"Dar'a","ADM2":"Dar'a","ADM3":"Ash-Shajara","ADM4":"Ash-Shajara","name":"Ash Shajarah IDP Camp 02","pcode":"SY120003C6021","location":"32.777,35.883"}
{"type":"idp","description":"IDP Camp","country":"Syria","ADM1":"Dar'a","ADM2":"Dar'a","ADM3":"Busra Esh-Sham","ADM4":"Tisiya","name":"Tisiya IDP Camp","pcode":"SY120001C6000","location":"32.418,36.457"}
{"type":"idp","description":"IDP Camp","country":"Syria","ADM1":"Halab","ADM2":"Afrin","ADM3":"Afrin","ADM4":"Baselhaya","name":"Basselhaya IDP Camp","pcode":"SY020300C1371","location":"36.467,36.951"}
{"type":"idp","description":"IDP Camp","country":"Syria","ADM1":"Halab","ADM2":"Afrin","ADM3":"Jandairis","ADM4":"Deir Ballut","name":"Dayr Ballut Atimah IDP Camp","pcode":"SY020302C1435","location":"36.323,36.661"}
{"type":"idp","description":"IDP Camp","country":"Syria","ADM1":"Halab","ADM2":"Ain Al Arab","ADM3":"Ain Al Arab","ADM4":"Ain Al Arab","name":"Kobane Ayn al Arab IDP Camp","pcode":"SY020600C1946","location":"36.894,38.331"}
{"type":"idp","description":"IDP Camp","country":"Syria","ADM1":"Halab","ADM2":"A'zaz","ADM3":"A'zaz","ADM4":"Salama","name":"Azaz Border Crossing Refugee Camp","pcode":"SY020400C1561","location":"36.632,37.084"}
{"type":"idp","description":"IDP Camp","country":"Syria","ADM1":"Halab","ADM2":"A'zaz","ADM3":"A'zaz","ADM4":"Salama","name":"Qassarjah Sudji IDP Camp","pcode":"SY020400C1561","location":"36.623,37.092"}
{"type":"idp","description":"IDP Camp","country":"Syria","ADM1":"Halab","ADM2":"A'zaz","ADM3":"A'zaz","ADM4":"Shamarin","name":"Shamarin IDP Camp North","pcode":"SY020400C1566","location":"36.661,37.136"}
{"type":"idp","description":"IDP Camp","country":"Syria","ADM1":"Halab","ADM2":"A'zaz","ADM3":"A'zaz","ADM4":"Shamarin","name":"Shamarin IDP Camp West","pcode":"SY020400C1566","location":"36.653,37.128"}
{"type":"idp","description":"IDP Camp","country":"Syria","ADM1":"Halab","ADM2":"A'zaz","ADM3":"A'zaz","ADM4":"Shamarin","name":"Sharmarin Camp","pcode":"SY020400C1566","location":"36.654,37.14"}
{"type":"idp","description":"IDP Camp","country":"Syria","ADM1":"Halab","ADM2":"A'zaz","ADM3":"Suran","ADM4":"Zayzafun -Ekdeh","name":"Ikadah IDP Camp","pcode":"SY020405C1658","location":"36.66,37.182"}
{"type":"idp","description":"IDP Camp","country":"Syria","ADM1":"Halab","ADM2":"Jarablus","ADM3":"Jarablus","ADM4":"Jarablus","name":"Jarabulus IDP Camp","pcode":"SY020800C2227","location":"36.824,38.012"}
{"type":"idp","description":"IDP Camp","country":"Syria","ADM1":"Homs","ADM2":"Homs","ADM3":"Hasyaa","ADM4":"Hasyaa","name":"Hisyah IDP Camp","pcode":"SY040108C2675","location":"34.404,36.764"}
{"type":"idp","description":"IDP Camp","country":"Syria","ADM1":"Idlib","ADM2":"Dana","ADM3":"Harim","ADM4":"Qah","name":"Atimah IDP Camp Southeast","pcode":"SY070301C4131","location":"36.293,36.701"}
{"type":"idp","description":"IDP Camp","country":"Syria","ADM1":"Idlib","ADM2":"Harim","ADM3":"Dana","ADM4":"Aqrabat","name":"Aqrabat IDP Camp","pcode":"SY070301C4127","location":"36.277,36.723"}
{"type":"idp","description":"IDP Camp","country":"Syria","ADM1":"Idlib","ADM2":"Harim","ADM3":"Dana","ADM4":"Aqrabat","name":"Aqrabat Southwest IDP Camp","pcode":"SY070301C4127","location":"36.266,36.702"}
{"type":"idp","description":"IDP Camp","country":"Syria","ADM1":"Idlib","ADM2":"Harim","ADM3":"Dana","ADM4":"Aqrabat","name":"Kafaldin North IDP Camp","pcode":"SY070301C4127","location":"36.268,36.721"}
{"type":"idp","description":"IDP Camp","country":"Syria","ADM1":"Idlib","ADM2":"Harim","ADM3":"Dana","ADM4":"Aqrabat","name":"Kafaldn Meydan IDP Camp","pcode":"SY070301C4127","location":"36.263,36.729"}
{"type":"idp","description":"IDP Camp","country":"Syria","ADM1":"Idlib","ADM2":"Harim","ADM3":"Dana","ADM4":"Deir Hassan","name":"Bab al Hawa Lower IDP Camp","pcode":"SY070301C4129","location":"36.211,36.715"}
{"type":"idp","description":"IDP Camp","country":"Syria","ADM1":"Idlib","ADM2":"Harim","ADM3":"Dana","ADM4":"Deir Hassan","name":"Bab al Hawa Upper IDP Camp","pcode":"SY070301C4129","location":"36.213,36.715"}
{"type":"idp","description":"IDP Camp","country":"Syria","ADM1":"Idlib","ADM2":"Harim","ADM3":"Dana","ADM4":"Deir Hassan","name":"Sarmada IDP Camp","pcode":"SY070301C4129","location":"36.206,36.73"}
{"type":"idp","description":"IDP Camp","country":"Syria","ADM1":"Idlib","ADM2":"Harim","ADM3":"Dana","ADM4":"Deir Hassan","name":"Sarmada IDP Camp 02","pcode":"SY070301C4129","location":"36.209,36.723"}
{"type":"idp","description":"IDP Camp","country":"Syria","ADM1":"Idlib","ADM2":"Harim","ADM3":"Dana","ADM4":"Deir Hassan","name":"Sarmada IDP Camp 03","pcode":"SY070301C4129","location":"36.204,36.734"}
{"type":"idp","description":"IDP Camp","country":"Syria","ADM1":"Idlib","ADM2":"Harim","ADM3":"Dana","ADM4":"Qah","name":"Qah IDP Camp","pcode":"SY070301C4131","location":"36.293,36.728"}
{"type":"idp","description":"IDP Camp","country":"Syria","ADM1":"Idlib","ADM2":"Harim","ADM3":"Dana","ADM4":"Qah","name":"Qah Southwest IDP Camp","pcode":"SY070301C4131","location":"36.283,36.719"}
{"type":"idp","description":"IDP Camp","country":"Syria","ADM1":"Idlib","ADM2":"Harim","ADM3":"Dana","ADM4":"Qah","name":"Qah West IDP Camp","pcode":"SY070301C4131","location":"36.29,36.711"}
{"type":"idp","description":"IDP Camp","country":"Syria","ADM1":"Idlib","ADM2":"Harim","ADM3":"Dana","ADM4":"Sarmada","name":"Dar Kuwayta Camp Northeast","pcode":"SY070301C4121","location":"36.218,36.693"}
{"type":"idp","description":"IDP Camp","country":"Syria","ADM1":"Idlib","ADM2":"Harim","ADM3":"Dana","ADM4":"Sarmada","name":"Sarfud IDP Camp","pcode":"SY070301C4121","location":"36.183,36.691"}
{"type":"idp","description":"IDP Camp","country":"Syria","ADM1":"Idlib","ADM2":"Harim","ADM3":"Dana","ADM4":"Sarmada","name":"Shaykh Hasan Camp Southwest","pcode":"SY070301C4121","location":"36.201,36.71"}
{"type":"idp","description":"IDP Camp","country":"Syria","ADM1":"Idlib","ADM2":"Harim","ADM3":"Harim","ADM4":"Harim","name":"Baraka Khirbat Kisah IDP Camp","pcode":"SY070300C4115","location":"36.227,36.561"}
{"type":"idp","description":"IDP Camp","country":"Syria","ADM1":"Idlib","ADM2":"Harim","ADM3":"Harim","ADM4":"Kafr Hum","name":"Kafr Hum IDP Camp","pcode":"SY070300C4117","location":"36.198,36.474"}
{"type":"idp","description":"IDP Camp","country":"Syria","ADM1":"Idlib","ADM2":"Harim","ADM3":"Salqin","ADM4":"Bozanti","name":"Muzanta IDP Camp","pcode":"SY070302C4144","location":"36.175,36.406"}
{"type":"idp","description":"IDP Camp","country":"Syria","ADM1":"Idlib","ADM2":"Harim","ADM3":"Salqin","ADM4":"Kafarna","name":"Khirbat Farraziyah Athme MSF Harem IDP Camp","pcode":"SY070302C4149","location":"36.197,36.432"}
{"type":"idp","description":"IDP Camp","country":"Syria","ADM1":"Idlib","ADM2":"Harim","ADM3":"Salqin","ADM4":"Kafr Jat","name":"Kafr Jat IDP Camp","pcode":"SY070302C4139","location":"36.182,36.432"}
{"type":"idp","description":"IDP Camp","country":"Syria","ADM1":"Idlib","ADM2":"Jisr-Ash-Shugur","ADM3":"Badama","ADM4":"Badama","name":"Al Hambushiyah IDP Camp","pcode":"SY070401C4226","location":"35.831,36.192"}
{"type":"idp","description":"IDP Camp","country":"Syria","ADM1":"Idlib","ADM2":"Jisr-Ash-Shugur","ADM3":"Badama","ADM4":"Badama","name":"Ubin IDP Camp","pcode":"SY070401C4226","location":"35.804,36.158"}
{"type":"idp","description":"IDP Camp","country":"Syria","ADM1":"Idlib","ADM2":"Jisr-Ash-Shugur","ADM3":"Jisr-Ash-Shugur","ADM4":"Dgali","name":"Qirmidah IDP Camp","pcode":"SY070400C4214","location":"35.914,36.379"}
{"type":"idp","description":"IDP Camp","country":"Syria","ADM1":"Latakia","ADM2":"Lattakia","ADM3":"Hanadi","ADM4":"Shir","name":"Rudu IDP Camp","pcode":"SY060006C3563","location":"35.541,35.85"}
{"type":"idp","description":"IDP Camp","country":"Syria","ADM1":"Latakia","ADM2":"Lattakia","ADM3":"Lattakia","ADM4":"Burj Elqasab","name":"Latakia Aquatic Sports Facility IDP Camp","pcode":"SY060000C3474","location":"35.56,35.748"}
{"type":"idp","description":"IDP Camp","country":"Syria","ADM1":"Latakia","ADM2":"Lattakia","ADM3":"Rebee'a","ADM4":"Samira - Sallur","name":"Qarah Bibar IDP Camp ","pcode":"SY060002C3501","location":"35.857,36.111"}
{"type":"idp","description":"IDP Camp","country":"Syria","ADM1":"Latakia","ADM2":"Lattakia","ADM3":"Rebee'a","ADM4":"Samira - Sallur","name":"Yamadiyah IDP Camp ","pcode":"SY060002C3501","location":"35.841,36.134"}
{"type":"idp","description":"IDP Camp","country":"Syria","ADM1":"Latakia","ADM2":"Lattakia","ADM3":"Rebee'a","ADM4":"Samira - Sallur","name":"Yamadiyah South IDP Camp","pcode":"SY060002C3501","location":"35.825,36.134"}
{"type":"idp","description":"IDP Camp","country":"Syria","ADM1":"Latakia","ADM2":"Lattakia","ADM3":"Rebee'a","ADM4":"Samira - Sallur","name":"Zaytunjuq IDP Camp","pcode":"SY060002C3501","location":"35.819,36.134"}
{"type":"idp","description":"IDP Camp","country":"Syria","ADM1":"Tartus","ADM2":"Tartous","ADM3":"Tartous","ADM4":"Ennabiya","name":"Hayy ar Radar IDP Camp","pcode":"SY100000C5238","location":"34.858,35.893"}
{"type":"idp","description":"IDP Camp","country":"Syria","ADM1":"Tartus","ADM2":"Tartous","ADM3":"Tartous","ADM4":"Ennabiya","name":"Shirkat As Sahil IDP Camp","pcode":"SY100000C5238","location":"34.851,35.907"}
{"type":"idp","description":"IDP Camp","country":"Syria","ADM1":"Tartus","ADM2":"Tartous","ADM3":"Tartous","ADM4":"Hisheh","name":"Al Hishah IDP Camp","pcode":"SY100000C5243","location":"34.787,35.926"}
{"type":"idp","description":"IDP Camp","country":"Syria","ADM1":"Tartus","ADM2":"Tartous","ADM3":"Tartous","ADM4":"Tartous","name":"Tartus IDP Camp","pcode":"SY100000C5221","location":"34.891,35.889"}
